LICENSE
MANIFEST.in
README.rst
setup.cfg
setup.py
numpyarray_to_latex/__init__.py
numpyarray_to_latex/jupyter.py
numpyarray_to_latex/main.py
numpyarray_to_latex/metadata.py
numpyarray_to_latex/utils.py
numpyarray_to_latex.egg-info/PKG-INFO
numpyarray_to_latex.egg-info/SOURCES.txt
numpyarray_to_latex.egg-info/dependency_links.txt
numpyarray_to_latex.egg-info/not-zip-safe
numpyarray_to_latex.egg-info/requires.txt
numpyarray_to_latex.egg-info/top_level.txt
numpyarray_to_latex/tests/__init__.py
numpyarray_to_latex/tests/tests.py