Metadata-Version: 1.2
Name: numpyarray-to-latex
Version: 0.0.3
Summary: Format numpy arrays as LaTeX arrays.
Home-page: https://github.com/benmaier/numpyarray_to_latex
Author: Joseph C. Slater and Benjamin F. Maier
Author-email: bfmaier@physik.hu-berlin.de
License: MIT
Project-URL: Documentation, https://numpyarray-to-latex.readthedocs.io
Project-URL: Contributing Statement, https://github.com/benmaier/numpyarray_to_latex/blob/master/CONTRIBUTING.md
Project-URL: Bug Reports, https://github.com/benmaier/numpyarray_to_latex/issues
Project-URL: Source, https://github.com/benmaier/numpyarray_to_latex/
Project-URL: PyPI, https://pypi.org/project/numpyarray_to_latex/
Platform: UNKNOWN
Classifier: License :: OSI Approved :: MIT License
Classifier: Programming Language :: Python :: 3.6
Classifier: Programming Language :: Python :: 3.7
Classifier: Programming Language :: Python :: 3.8
Classifier: Programming Language :: Python :: 3.9
Classifier: Programming Language :: Python :: 3.10
Requires-Python: >=3.6
